{
  "en": {
    "name": "Keisuke Kido",
    "title": "Software Engineer",
    "page.about.title": "About",
    "page.home.title": "Hi, I'm Keisuke Kido",
    "page.home.description": "I'm a fullstack web developer based in Japan. Outside of work, I like the growing pains from build things with Haskell.",
    "page.posts.title": "Posts",
    "page.tags.title": "Tags",
    "navigation.about": "About",
    "navigation.home": "Home",
    "navigation.posts": "Posts",
    "navigation.tags": "Tags",
    "article.next": "Next",
    "article.previous": "Previous",
    "contact-me": "Contact Me",
    "recent-posts": "Recent Posts",
    "socials": "Contact",
    "resume": "Resume",
    "resume.en": "Resume en",
    "resume.ja": "Resume ja",
    "view-all": "View All",
    "page-search.close": "Close",
    "email": "Email",
    "linkedin": "Linkedin",
    "github": "Github",
    "en": "English",
    "ja": "日本語"
  },
  "ja": {
    "name": "貴堂慶祐",
    "title": "ソフトウェアエンジニア",
    "page.about.title": "プロフィール",
    "page.home.title": "Hi, I'm Keisuke Kido",
    "page.home.description": "日本在住のよくいるフルスタックウェブエンジニアです。Haskellが好きです。",
    "page.posts.title": "投稿一覧",
    "page.tags.title": "タグ一覧",
    "navigation.about": "プロフィール",
    "navigation.home": "ホーム",
    "navigation.posts": "投稿一覧",
    "navigation.tags": "タグ一覧",
    "article.next": "次の投稿",
    "article.previous": "前の投稿",
    "recent-posts": "最近の投稿",
    "socials": "アカウント各種",
    "resume": "職務履歴",
    "resume.en": "職務履歴（英）",
    "resume.ja": "職務履歴（日）",
    "contact-me": "連絡先",
    "view-all": "全て表示",
    "page-search.close": "閉じる",
    "email": "メール",
    "linkedin": "Linkedin",
    "github": "Github",
    "en": "English",
    "ja": "日本語"
  }
}
